Workbook

Sheet Summary
A1: Netflix, Inc. (NFLX) — Valuation Summary
A2: DCF (FCF-margin) + comparable companies · base year FY2025
A4: Reference price ($) | C4: =WACC!C15 -> 110
A5: WACC (base case) | C5: =WACC!C24 -> 0.10819203
A7: Intrinsic value per share
A8: Bear case | C8: =DCF!C38 -> 35.234672
A9: Base case | C9: =DCF!C52 -> 52.350875
A10: Bull case | C10: =DCF!C66 -> 115.21862
A11: Comps (average) | C11: =Comps!F19 -> 49.856374
A13: Cross-checks
A14: Base-case enterprise value ($mm) | C14: =DCF!C50 -> 226380.69
A15: Terminal value % of EV (base) | C15: =DCF!C49/DCF!C50 -> 0.73939457
A17: Valuation range (football field)
A18: Bear | C18: =C8 -> 35.234672
A19: Comps | C19: =C11 -> 49.856374
A20: Base | C20: =C9 -> 52.350875
A21: Bull | C21: =C10 -> 115.21862
A24: Key caveats
A25: Standalone Netflix — the pending all-cash Warner Bros. acquisition (Dec-2025)
A26: is NOT modelled and would change debt, shares and the growth profile.
A27: Peer multiples are illustrative placeholders; refresh before citing.
A28: Share price is a post-split reference (10:1, Nov-2025) — update to live quote.
A29: Educational / portfolio use only. Not investment advice.

Sheet WACC
A1: WACC — Cost of Capital
A3: Cost of equity (CAPM)
A4: Risk-free rate (10Y UST) | C4: 0.043
A5: Beta (5y) | C5: 1.2
A6: Equity risk premium | C6: 0.055
A7: Cost of equity | C7: =C4+C5*C6 -> 0.109
A9: Cost of debt
A10: Pre-tax cost of debt | C10: 0.05
A11: Tax rate | C11: 0.21
A12: After-tax cost of debt | C12: =C10*(1-C11) -> 0.0395
A14: Capital structure
A15: Share price ($) | C15: 110
A16: Shares outstanding (mm) | C16: 4220
A17: Market capitalisation ($mm) | C17: =C15*C16 -> 464200
A18: Total debt ($mm) | C18: 14460
A19: Cash & equivalents ($mm) | C19: 9000
A20: Net debt ($mm) | C20: =C18-C19 -> 5460
A21: Equity weight | C21: =C17/(C17+MAX(C20,0)) -> 0.98837457
A22: Debt weight | C22: =MAX(C20,0)/(C17+MAX(C20,0)) -> 0.011625431
A24: WACC | C24: =C7*C21+C12*C22 -> 0.10819203

Sheet DCF
A1: Netflix, Inc. (NFLX) — DCF Model
A2: FCF-margin method · 5-year explicit forecast · mid-year convention · $mm
A4: Assumptions
A5: Base-year revenue FY2025 ($mm) | C5: 45183
A6: Net debt ($mm) | C6: =WACC!C20 -> 5460
A7: Shares outstanding (mm) | C7: =WACC!C16 -> 4220
A8: Reference price ($) | C8: =WACC!C15 -> 110
A10: Revenue growth by case | D10: 2026 | E10: 2027 | F10: 2028 | G10: 2029 | H10: 2030
A11: Bear | D11: 0.1 | E11: 0.09 | F11: 0.08 | G11: 0.07 | H11: 0.06
A12: Base | D12: 0.13 | E12: 0.12 | F12: 0.11 | G12: 0.09 | H12: 0.08
A13: Bull | D13: 0.17 | E13: 0.16 | F13: 0.14 | G13: 0.12 | H13: 0.11
A15: FCF margin by case (% of revenue) | D15: 2026 | E15: 2027 | F15: 2028 | G15: 2029 | H15: 2030
A16: Bear | D16: 0.2 | E16: 0.21 | F16: 0.22 | G16: 0.22 | H16: 0.23
A17: Base | D17: 0.21 | E17: 0.23 | F17: 0.25 | G17: 0.26 | H17: 0.27
A18: Bull | D18: 0.23 | E18: 0.26 | F18: 0.29 | G18: 0.31 | H18: 0.33
A20: Discount rate & terminal growth by case | C20: WACC | D20: Terminal g
A21: Bear | C21: 0.115 | D21: 0.025
A22: Base | C22: =WACC!C24 -> 0.10819203 | D22: 0.03
A23: Bull | C23: 0.085 | D23: 0.035
A25: Discount period (mid-year) | D25: 0.5 | E25: =D25+1 -> 1.5 | F25: =E25+1 -> 2.5 | G25: =F25+1 -> 3.5 | H25: =G25+1 -> 4.5
A27: BEAR CASE
D28: 2026 | E28: 2027 | F28: 2028 | G28: 2029 | H28: 2030
A29: Revenue ($mm) | D29: =$C$5*(1+D$11) -> 49701.3 | E29: =D29*(1+E$11) -> 54174.417 | F29: =E29*(1+F$11) -> 58508.37 | G29: =F29*(1+G$11) -> 62603.956 | H29: =G29*(1+H$11) -> 66360.194
A30: Free cash flow ($mm) | D30: =D29*D$16 -> 9940.26 | E30: =E29*E$16 -> 11376.628 | F30: =F29*F$16 -> 12871.841 | G30: =G29*G$16 -> 13772.87 | H30: =H29*H$16 -> 15262.845
A31: Discount factor | D31: =1/(1+$C$21)^D$25 -> 0.94702745 | E31: =1/(1+$C$21)^E$25 -> 0.84935197 | F31: =1/(1+$C$21)^F$25 -> 0.76175065 | G31: =1/(1+$C$21)^G$25 -> 0.68318444 | H31: =1/(1+$C$21)^H$25 -> 0.61272147
A32: PV of FCF ($mm) | D32: =D30*D31 -> 9413.6991 | E32: =E30*E31 -> 9662.761 | F32: =F30*F31 -> 9805.1336 | G32: =G30*G31 -> 9409.4107 | H32: =H30*H31 -> 9351.8725
B33: Sum PV of explicit FCF | C33: =SUM(D32:H32) -> 47642.877
B34: Terminal value (Gordon) | C34: =H30*(1+$D$21)/($C$21-$D$21) -> 173826.84
B35: PV of terminal value | C35: =C34*H31 -> 106507.44
B36: Enterprise value | C36: =C33+C35 -> 154150.31
B37: Less: net debt → Equity value | C37: =C36-$C$6 -> 148690.31
B38: Value per share ($) | C38: =C37/$C$7 -> 35.234672
B39: Upside / (downside) vs price | C39: =C38/$C$8-1 -> -0.6796848
A41: BASE CASE
D42: 2026 | E42: 2027 | F42: 2028 | G42: 2029 | H42: 2030
A43: Revenue ($mm) | D43: =$C$5*(1+D$12) -> 51056.79 | E43: =D43*(1+E$12) -> 57183.605 | F43: =E43*(1+F$12) -> 63473.801 | G43: =F43*(1+G$12) -> 69186.443 | H43: =G43*(1+H$12) -> 74721.359
A44: Free cash flow ($mm) | D44: =D43*D$17 -> 10721.926 | E44: =E43*E$17 -> 13152.229 | F44: =F43*F$17 -> 15868.45 | G44: =G43*G$17 -> 17988.475 | H44: =H43*H$17 -> 20174.767
A45: Discount factor | D45: =1/(1+$C$22)^D$25 -> 0.94993194 | E45: =1/(1+$C$22)^E$25 -> 0.85719073 | F45: =1/(1+$C$22)^F$25 -> 0.77350378 | G45: =1/(1+$C$22)^G$25 -> 0.69798714 | H45: =1/(1+$C$22)^H$25 -> 0.62984313
A46: PV of FCF ($mm) | D46: =D44*D45 -> 10185.1 | E46: =E44*E45 -> 11273.969 | F46: =F44*F45 -> 12274.306 | G46: =G44*G45 -> 12555.724 | H46: =H44*H45 -> 12706.938
B47: Sum PV of explicit FCF | C47: =SUM(D46:H46) -> 58996.038
B48: Terminal value (Gordon) | C48: =H44*(1+$D$22)/($C$22-$D$22) -> 265756.1
B49: PV of terminal value | C49: =C48*H45 -> 167384.66
B50: Enterprise value | C50: =C47+C49 -> 226380.69
B51: Less: net debt → Equity value | C51: =C50-$C$6 -> 220920.69
B52: Value per share ($) | C52: =C51/$C$7 -> 52.350875
B53: Upside / (downside) vs price | C53: =C52/$C$8-1 -> -0.52408295
A55: BULL CASE
D56: 2026 | E56: 2027 | F56: 2028 | G56: 2029 | H56: 2030
A57: Revenue ($mm) | D57: =$C$5*(1+D$13) -> 52864.11 | E57: =D57*(1+E$13) -> 61322.368 | F57: =E57*(1+F$13) -> 69907.499 | G57: =F57*(1+G$13) -> 78296.399 | H57: =G57*(1+H$13) -> 86909.003
A58: Free cash flow ($mm) | D58: =D57*D$18 -> 12158.745 | E58: =E57*E$18 -> 15943.816 | F58: =F57*F$18 -> 20273.175 | G58: =G57*G$18 -> 24271.884 | H58: =H57*H$18 -> 28679.971
A59: Discount factor | D59: =1/(1+$C$23)^D$25 -> 0.96003072 | E59: =1/(1+$C$23)^E$25 -> 0.88482094 | F59: =1/(1+$C$23)^F$25 -> 0.81550317 | G59: =1/(1+$C$23)^G$25 -> 0.75161583 | H59: =1/(1+$C$23)^H$25 -> 0.69273348
A60: PV of FCF ($mm) | D60: =D58*D59 -> 11672.769 | E60: =E58*E59 -> 14107.422 | F60: =F58*F59 -> 16532.838 | G60: =G58*G59 -> 18243.132 | H60: =H58*H59 -> 19867.576
B61: Sum PV of explicit FCF | C61: =SUM(D60:H60) -> 80423.737
B62: Terminal value (Gordon) | C62: =H58*(1+$D$23)/($C$23-$D$23) -> 593675.4
B63: PV of terminal value | C63: =C62*H59 -> 411258.83
B64: Enterprise value | C64: =C61+C63 -> 491682.56
B65: Less: net debt → Equity value | C65: =C64-$C$6 -> 486222.56
B66: Value per share ($) | C66: =C65/$C$7 -> 115.21862
B67: Upside / (downside) vs price | C67: =C66/$C$8-1 -> 0.04744197
A70: Sensitivity — base-case value/share: WACC (down) × terminal g (across)
B71: WACC ↓ / g → | D71: =E71-0.005 -> 0.02 | E71: =F71-0.005 -> 0.025 | F71: =$D$22 -> 0.03 | G71: =F71+0.005 -> 0.035 | H71: =G71+0.005 -> 0.04
C72: =C73-0.01 -> 0.088192033 | D72: =(SUMPRODUCT($D$44:$H$44,1/(1+$C72)^($D$25:$H$25))+$H$44*(1+D$71)/($C72-D$71)/(1+$C72)^$H$25-$C$6)/$C$7 -> 62.25718 | E72: =(SUMPRODUCT($D$44:$H$44,1/(1+$C72)^($D$25:$H$25))+$H$44*(1+E$71)/($C72-E$71)/(1+$C72)^$H$25-$C$6)/$C$7 -> 66.38386 | F72: =(SUMPRODUCT($D$44:$H$44,1/(1+$C72)^($D$25:$H$25))+$H$44*(1+F$71)/($C72-F$71)/(1+$C72)^$H$25-$C$6)/$C$7 -> 71.219687 | G72: =(SUMPRODUCT($D$44:$H$44,1/(1+$C72)^($D$25:$H$25))+$H$44*(1+G$71)/($C72-G$71)/(1+$C72)^$H$25-$C$6)/$C$7 -> 76.964642 | H72: =(SUMPRODUCT($D$44:$H$44,1/(1+$C72)^($D$25:$H$25))+$H$44*(1+H$71)/($C72-H$71)/(1+$C72)^$H$25-$C$6)/$C$7 -> 83.901692
C73: =C74-0.01 -> 0.098192033 | D73: =(SUMPRODUCT($D$44:$H$44,1/(1+$C73)^($D$25:$H$25))+$H$44*(1+D$71)/($C73-D$71)/(1+$C73)^$H$25-$C$6)/$C$7 -> 53.936638 | E73: =(SUMPRODUCT($D$44:$H$44,1/(1+$C73)^($D$25:$H$25))+$H$44*(1+E$71)/($C73-E$71)/(1+$C73)^$H$25-$C$6)/$C$7 -> 56.94594 | F73: =(SUMPRODUCT($D$44:$H$44,1/(1+$C73)^($D$25:$H$25))+$H$44*(1+F$71)/($C73-F$71)/(1+$C73)^$H$25-$C$6)/$C$7 -> 60.39654 | G73: =(SUMPRODUCT($D$44:$H$44,1/(1+$C73)^($D$25:$H$25))+$H$44*(1+G$71)/($C73-G$71)/(1+$C73)^$H$25-$C$6)/$C$7 -> 64.39319 | H73: =(SUMPRODUCT($D$44:$H$44,1/(1+$C73)^($D$25:$H$25))+$H$44*(1+H$71)/($C73-H$71)/(1+$C73)^$H$25-$C$6)/$C$7 -> 69.076644
C74: =$C$22 -> 0.10819203 | D74: =(SUMPRODUCT($D$44:$H$44,1/(1+$C74)^($D$25:$H$25))+$H$44*(1+D$71)/($C74-D$71)/(1+$C74)^$H$25-$C$6)/$C$7 -> 47.51192 | E74: =(SUMPRODUCT($D$44:$H$44,1/(1+$C74)^($D$25:$H$25))+$H$44*(1+E$71)/($C74-E$71)/(1+$C74)^$H$25-$C$6)/$C$7 -> 49.785982 | F74: =(SUMPRODUCT($D$44:$H$44,1/(1+$C74)^($D$25:$H$25))+$H$44*(1+F$71)/($C74-F$71)/(1+$C74)^$H$25-$C$6)/$C$7 -> 52.350875 | G74: =(SUMPRODUCT($D$44:$H$44,1/(1+$C74)^($D$25:$H$25))+$H$44*(1+G$71)/($C74-G$71)/(1+$C74)^$H$25-$C$6)/$C$7 -> 55.266202 | H74: =(SUMPRODUCT($D$44:$H$44,1/(1+$C74)^($D$25:$H$25))+$H$44*(1+H$71)/($C74-H$71)/(1+$C74)^$H$25-$C$6)/$C$7 -> 58.609045
C75: =C74+0.01 -> 0.11819203 | D75: =(SUMPRODUCT($D$44:$H$44,1/(1+$C75)^($D$25:$H$25))+$H$44*(1+D$71)/($C75-D$71)/(1+$C75)^$H$25-$C$6)/$C$7 -> 42.403454 | E75: =(SUMPRODUCT($D$44:$H$44,1/(1+$C75)^($D$25:$H$25))+$H$44*(1+E$71)/($C75-E$71)/(1+$C75)^$H$25-$C$6)/$C$7 -> 44.17032 | F75: =(SUMPRODUCT($D$44:$H$44,1/(1+$C75)^($D$25:$H$25))+$H$44*(1+F$71)/($C75-F$71)/(1+$C75)^$H$25-$C$6)/$C$7 -> 46.137529 | G75: =(SUMPRODUCT($D$44:$H$44,1/(1+$C75)^($D$25:$H$25))+$H$44*(1+G$71)/($C75-G$71)/(1+$C75)^$H$25-$C$6)/$C$7 -> 48.341205 | H75: =(SUMPRODUCT($D$44:$H$44,1/(1+$C75)^($D$25:$H$25))+$H$44*(1+H$71)/($C75-H$71)/(1+$C75)^$H$25-$C$6)/$C$7 -> 50.826709
C76: =C75+0.01 -> 0.12819203 | D76: =(SUMPRODUCT($D$44:$H$44,1/(1+$C76)^($D$25:$H$25))+$H$44*(1+D$71)/($C76-D$71)/(1+$C76)^$H$25-$C$6)/$C$7 -> 38.245962 | E76: =(SUMPRODUCT($D$44:$H$44,1/(1+$C76)^($D$25:$H$25))+$H$44*(1+E$71)/($C76-E$71)/(1+$C76)^$H$25-$C$6)/$C$7 -> 39.649694 | F76: =(SUMPRODUCT($D$44:$H$44,1/(1+$C76)^($D$25:$H$25))+$H$44*(1+F$71)/($C76-F$71)/(1+$C76)^$H$25-$C$6)/$C$7 -> 41.196383 | G76: =(SUMPRODUCT($D$44:$H$44,1/(1+$C76)^($D$25:$H$25))+$H$44*(1+G$71)/($C76-G$71)/(1+$C76)^$H$25-$C$6)/$C$7 -> 42.90904 | H76: =(SUMPRODUCT($D$44:$H$44,1/(1+$C76)^($D$25:$H$25))+$H$44*(1+H$71)/($C76-H$71)/(1+$C76)^$H$25-$C$6)/$C$7 -> 44.815894
A79: Sensitivity — value/share: flat revenue growth (down) × flat FCF margin (across)
B80: growth ↓ / margin → | D80: =E80-0.02 -> 0.21 | E80: =F80-0.02 -> 0.23 | F80: 0.25 | G80: =F80+0.02 -> 0.27 | H80: =G80+0.02 -> 0.29
C81: =C82-0.02 -> 0.06 | D81: =(D$80*$C$5*SUMPRODUCT((1+$C81)^($D$25:$H$25+0.5),1/(1+$C$22)^($D$25:$H$25))+D$80*$C$5*(1+$C81)^5*(1+$D$22)/($C$22-$D$22)/(1+$C$22)^$H$25-$C$6)/$C$7 -> 34.047838 | E81: =(E$80*$C$5*SUMPRODUCT((1+$C81)^($D$25:$H$25+0.5),1/(1+$C$22)^($D$25:$H$25))+E$80*$C$5*(1+$C81)^5*(1+$D$22)/($C$22-$D$22)/(1+$C$22)^$H$25-$C$6)/$C$7 -> 37.413712 | F81: =(F$80*$C$5*SUMPRODUCT((1+$C81)^($D$25:$H$25+0.5),1/(1+$C$22)^($D$25:$H$25))+F$80*$C$5*(1+$C81)^5*(1+$D$22)/($C$22-$D$22)/(1+$C$22)^$H$25-$C$6)/$C$7 -> 40.779586 | G81: =(G$80*$C$5*SUMPRODUCT((1+$C81)^($D$25:$H$25+0.5),1/(1+$C$22)^($D$25:$H$25))+G$80*$C$5*(1+$C81)^5*(1+$D$22)/($C$22-$D$22)/(1+$C$22)^$H$25-$C$6)/$C$7 -> 44.14546 | H81: =(H$80*$C$5*SUMPRODUCT((1+$C81)^($D$25:$H$25+0.5),1/(1+$C$22)^($D$25:$H$25))+H$80*$C$5*(1+$C81)^5*(1+$D$22)/($C$22-$D$22)/(1+$C$22)^$H$25-$C$6)/$C$7 -> 47.511334
C82: =C83-0.02 -> 0.08 | D82: =(D$80*$C$5*SUMPRODUCT((1+$C82)^($D$25:$H$25+0.5),1/(1+$C$22)^($D$25:$H$25))+D$80*$C$5*(1+$C82)^5*(1+$D$22)/($C$22-$D$22)/(1+$C$22)^$H$25-$C$6)/$C$7 -> 37.077684 | E82: =(E$80*$C$5*SUMPRODUCT((1+$C82)^($D$25:$H$25+0.5),1/(1+$C$22)^($D$25:$H$25))+E$80*$C$5*(1+$C82)^5*(1+$D$22)/($C$22-$D$22)/(1+$C$22)^$H$25-$C$6)/$C$7 -> 40.732114 | F82: =(F$80*$C$5*SUMPRODUCT((1+$C82)^($D$25:$H$25+0.5),1/(1+$C$22)^($D$25:$H$25))+F$80*$C$5*(1+$C82)^5*(1+$D$22)/($C$22-$D$22)/(1+$C$22)^$H$25-$C$6)/$C$7 -> 44.386545 | G82: =(G$80*$C$5*SUMPRODUCT((1+$C82)^($D$25:$H$25+0.5),1/(1+$C$22)^($D$25:$H$25))+G$80*$C$5*(1+$C82)^5*(1+$D$22)/($C$22-$D$22)/(1+$C$22)^$H$25-$C$6)/$C$7 -> 48.040976 | H82: =(H$80*$C$5*SUMPRODUCT((1+$C82)^($D$25:$H$25+0.5),1/(1+$C$22)^($D$25:$H$25))+H$80*$C$5*(1+$C82)^5*(1+$D$22)/($C$22-$D$22)/(1+$C$22)^$H$25-$C$6)/$C$7 -> 51.695406
C83: 0.1 | D83: =(D$80*$C$5*SUMPRODUCT((1+$C83)^($D$25:$H$25+0.5),1/(1+$C$22)^($D$25:$H$25))+D$80*$C$5*(1+$C83)^5*(1+$D$22)/($C$22-$D$22)/(1+$C$22)^$H$25-$C$6)/$C$7 -> 40.324669 | E83: =(E$80*$C$5*SUMPRODUCT((1+$C83)^($D$25:$H$25+0.5),1/(1+$C$22)^($D$25:$H$25))+E$80*$C$5*(1+$C83)^5*(1+$D$22)/($C$22-$D$22)/(1+$C$22)^$H$25-$C$6)/$C$7 -> 44.288337 | F83: =(F$80*$C$5*SUMPRODUCT((1+$C83)^($D$25:$H$25+0.5),1/(1+$C$22)^($D$25:$H$25))+F$80*$C$5*(1+$C83)^5*(1+$D$22)/($C$22-$D$22)/(1+$C$22)^$H$25-$C$6)/$C$7 -> 48.252004 | G83: =(G$80*$C$5*SUMPRODUCT((1+$C83)^($D$25:$H$25+0.5),1/(1+$C$22)^($D$25:$H$25))+G$80*$C$5*(1+$C83)^5*(1+$D$22)/($C$22-$D$22)/(1+$C$22)^$H$25-$C$6)/$C$7 -> 52.215672 | H83: =(H$80*$C$5*SUMPRODUCT((1+$C83)^($D$25:$H$25+0.5),1/(1+$C$22)^($D$25:$H$25))+H$80*$C$5*(1+$C83)^5*(1+$D$22)/($C$22-$D$22)/(1+$C$22)^$H$25-$C$6)/$C$7 -> 56.179339
C84: =C83+0.02 -> 0.12 | D84: =(D$80*$C$5*SUMPRODUCT((1+$C84)^($D$25:$H$25+0.5),1/(1+$C$22)^($D$25:$H$25))+D$80*$C$5*(1+$C84)^5*(1+$D$22)/($C$22-$D$22)/(1+$C$22)^$H$25-$C$6)/$C$7 -> 43.800654 | E84: =(E$80*$C$5*SUMPRODUCT((1+$C84)^($D$25:$H$25+0.5),1/(1+$C$22)^($D$25:$H$25))+E$80*$C$5*(1+$C84)^5*(1+$D$22)/($C$22-$D$22)/(1+$C$22)^$H$25-$C$6)/$C$7 -> 48.095368 | F84: =(F$80*$C$5*SUMPRODUCT((1+$C84)^($D$25:$H$25+0.5),1/(1+$C$22)^($D$25:$H$25))+F$80*$C$5*(1+$C84)^5*(1+$D$22)/($C$22-$D$22)/(1+$C$22)^$H$25-$C$6)/$C$7 -> 52.390082 | G84: =(G$80*$C$5*SUMPRODUCT((1+$C84)^($D$25:$H$25+0.5),1/(1+$C$22)^($D$25:$H$25))+G$80*$C$5*(1+$C84)^5*(1+$D$22)/($C$22-$D$22)/(1+$C$22)^$H$25-$C$6)/$C$7 -> 56.684795 | H84: =(H$80*$C$5*SUMPRODUCT((1+$C84)^($D$25:$H$25+0.5),1/(1+$C$22)^($D$25:$H$25))+H$80*$C$5*(1+$C84)^5*(1+$D$22)/($C$22-$D$22)/(1+$C$22)^$H$25-$C$6)/$C$7 -> 60.979509
C85: =C84+0.02 -> 0.14 | D85: =(D$80*$C$5*SUMPRODUCT((1+$C85)^($D$25:$H$25+0.5),1/(1+$C$22)^($D$25:$H$25))+D$80*$C$5*(1+$C85)^5*(1+$D$22)/($C$22-$D$22)/(1+$C$22)^$H$25-$C$6)/$C$7 -> 47.517927 | E85: =(E$80*$C$5*SUMPRODUCT((1+$C85)^($D$25:$H$25+0.5),1/(1+$C$22)^($D$25:$H$25))+E$80*$C$5*(1+$C85)^5*(1+$D$22)/($C$22-$D$22)/(1+$C$22)^$H$25-$C$6)/$C$7 -> 52.166667 | F85: =(F$80*$C$5*SUMPRODUCT((1+$C85)^($D$25:$H$25+0.5),1/(1+$C$22)^($D$25:$H$25))+F$80*$C$5*(1+$C85)^5*(1+$D$22)/($C$22-$D$22)/(1+$C$22)^$H$25-$C$6)/$C$7 -> 56.815407 | G85: =(G$80*$C$5*SUMPRODUCT((1+$C85)^($D$25:$H$25+0.5),1/(1+$C$22)^($D$25:$H$25))+G$80*$C$5*(1+$C85)^5*(1+$D$22)/($C$22-$D$22)/(1+$C$22)^$H$25-$C$6)/$C$7 -> 61.464146 | H85: =(H$80*$C$5*SUMPRODUCT((1+$C85)^($D$25:$H$25+0.5),1/(1+$C$22)^($D$25:$H$25))+H$80*$C$5*(1+$C85)^5*(1+$D$22)/($C$22-$D$22)/(1+$C$22)^$H$25-$C$6)/$C$7 -> 66.112886
A88: Note: flat-rate table holds WACC & terminal g at base; centre cell of the top table equals the base case.

Sheet Comps
A1: Comparable Company Analysis
A2: Peer multiples are ILLUSTRATIVE placeholders — refresh before citing. $mm.
A3: Ticker | B3: Revenue | C3: EBIT | D3: D&A | E3: EBITDA | F3: Net inc. | G3: Price | H3: Shares | I3: Debt | J3: Cash | K3: Mkt cap | L3: EV | M3: EV/Sales | N3: EV/EBITDA | O3: EV/EBIT | P3: P/E
A4: NFLX | B4: =DCF!$C$5 -> 45183 | C4: 13327 | D4: 16400 | E4: =C4+D4 -> 29727 | F4: 10981 | G4: =WACC!$C$15 -> 110 | H4: =WACC!$C$16 -> 4220 | I4: =WACC!$C$18 -> 14460 | J4: =WACC!$C$19 -> 9000 | K4: =G4*H4 -> 464200 | L4: =K4+I4-J4 -> 469660 | M4: =L4/B4 -> 10.394617 | N4: =L4/E4 -> 15.799105 | O4: =L4/C4 -> 35.24124 | P4: =IF(F4>0,K4/F4,"n/m") -> 42.273017
A5: CMCSA | B5: 124000 | C5: 24000 | D5: 14000 | E5: =C5+D5 -> 38000 | F5: 16000 | G5: 38 | H5: 3800 | I5: 100000 | J5: 6000 | K5: =G5*H5 -> 144400 | L5: =K5+I5-J5 -> 238400 | M5: =L5/B5 -> 1.9225806 | N5: =L5/E5 -> 6.2736842 | O5: =L5/C5 -> 9.9333333 | P5: =IF(F5>0,K5/F5,"n/m") -> 9.025
A6: DIS | B6: 94000 | C6: 12000 | D6: 5000 | E6: =C6+D6 -> 17000 | F6: 6000 | G6: 112 | H6: 1800 | I6: 45000 | J6: 6000 | K6: =G6*H6 -> 201600 | L6: =K6+I6-J6 -> 240600 | M6: =L6/B6 -> 2.5595745 | N6: =L6/E6 -> 14.152941 | O6: =L6/C6 -> 20.05 | P6: =IF(F6>0,K6/F6,"n/m") -> 33.6
A7: PSKY | B7: 29000 | C7: 2500 | D7: 1500 | E7: =C7+D7 -> 4000 | F7: 1000 | G7: 14 | H7: 700 | I7: 14000 | J7: 3000 | K7: =G7*H7 -> 9800 | L7: =K7+I7-J7 -> 20800 | M7: =L7/B7 -> 0.71724138 | N7: =L7/E7 -> 5.2 | O7: =L7/C7 -> 8.32 | P7: =IF(F7>0,K7/F7,"n/m") -> 9.8
A8: SPOT | B8: 18000 | C8: 1500 | D8: 200 | E8: =C8+D8 -> 1700 | F8: 1300 | G8: 600 | H8: 200 | I8: 1500 | J8: 8000 | K8: =G8*H8 -> 120000 | L8: =K8+I8-J8 -> 113500 | M8: =L8/B8 -> 6.3055556 | N8: =L8/E8 -> 66.764706 | O8: =L8/C8 -> 75.666667 | P8: =IF(F8>0,K8/F8,"n/m") -> 92.307692
A9: WBD | B9: 39000 | C9: 3000 | D9: 6000 | E9: =C9+D9 -> 9000 | F9: -3000 | G9: 18 | H9: 2500 | I9: 38000 | J9: 4000 | K9: =G9*H9 -> 45000 | L9: =K9+I9-J9 -> 79000 | M9: =L9/B9 -> 2.025641 | N9: =L9/E9 -> 8.7777778 | O9: =L9/C9 -> 26.333333 | P9: =IF(F9>0,K9/F9,"n/m") -> n/m
A11: Peer median (excl. NFLX) | M11: =MEDIAN(M5:M9) -> 2.025641 | N11: =MEDIAN(N5:N9) -> 8.7777778 | O11: =MEDIAN(O5:O9) -> 20.05 | P11: =MEDIAN(P5:P9) -> 21.7
A13: Implied value — Netflix
A14: Method | B14: Peer median | C14: NFLX metric | D14: Implied EV | E14: Implied equity | F14: Value/share
A15: EV/Sales | B15: =M11 -> 2.025641 | C15: =B4 -> 45183 | D15: =B15*C15 -> 91524.538 | E15: =D15-WACC!$C$20 -> 86064.538 | F15: =E15/WACC!$C$16 -> 20.39444
A16: EV/EBITDA | B16: =N11 -> 8.7777778 | C16: =E4 -> 29727 | D16: =B16*C16 -> 260937 | E16: =D16-WACC!$C$20 -> 255477 | F16: =E16/WACC!$C$16 -> 60.539573
A17: EV/EBIT | B17: =O11 -> 20.05 | C17: =C4 -> 13327 | D17: =B17*C17 -> 267206.35 | E17: =D17-WACC!$C$20 -> 261746.35 | F17: =E17/WACC!$C$16 -> 62.025201
A18: P/E | B18: =P11 -> 21.7 | C18: =F4 -> 10981 | D18: — | F18: =B18*C18/WACC!$C$16 -> 56.46628
A19: Average implied value/share | F19: =AVERAGE(F15:F18) -> 49.856374
